{"race:AL": [{"name": "Douglas Jones", "party": "Democratic", "path": "/al/candidate/douglas-jones"}, {"name": "Tommy Tuberville", "party": "Republican", "path": "/al/candidate/tommy-tuberville"}, {"name": "Ronald Fulton Burnette", "party": "Independent", "path": "/al/candidate/ronald-fulton-burnette"}, {"name": "Willie Boyd", "party": "Democratic", "path": "/al/candidate/willie-boyd"}, {"name": "Jamel Jermaine Brown", "party": "Democratic", "path": "/al/candidate/jamel-jermaine-brown"}, {"name": "Yolanda Flowers", "party": "Democratic", "path": "/al/candidate/yolanda-flowers"}, {"name": "Chad Chig Martin", "party": "Democratic", "path": "/al/candidate/chad-chig-martin"}, {"name": "Ken Mcfeeters", "party": "Republican", "path": "/al/candidate/ken-mcfeeters"}], "cand:/al/candidate/douglas-jones": {"coh": 0.0, "contributions": 0.0, "expenditures": 0.0}, "cand:/al/candidate/tommy-tuberville": {"coh": 0.0, "contributions": 13792994.0, "expenditures": 4689807.0}, "race:AZ": [{"name": "Leezah Sun", "party": "Independent", "path": "/az/candidate/leezah-sun-can"}, {"name": "Katie Hobbs", "party": "Democratic", "path": "/az/candidate/katie-hobbs-can"}, {"name": "William Pounds", "party": "Green", "path": "/az/candidate/william-pounds"}, {"name": "Teri Ann Hourihan", "party": "No Labels", "path": "/az/candidate/teri-ann-hourihan"}, {"name": "Andy Biggs", "party": "Republican", "path": "/az/candidate/andy-biggs"}, {"name": "Scott David Neely", "party": "Republican", "path": "/az/candidate/scott-david-neely"}, {"name": "David Schweikert", "party": "Republican", "path": "/az/candidate/david-schweikert"}, {"name": "Karrin Taylor Robson", "party": "Republican", "path": "/az/candidate/karrin-taylor-robson"}], "cand:/az/candidate/katie-hobbs-can": {"coh": 0.0, "contributions": 6534592.0, "expenditures": 3765166.0}, "cand:/az/candidate/andy-biggs": {"coh": 0.0, "contributions": 1923723.0, "expenditures": 1190844.0}, "race:CA": [{"name": "Xavier Becerra", "party": "Democratic", "path": "/ca/candidate/xavier-becerra"}, {"name": "Steve Hilton", "party": "Republican", "path": "/ca/candidate/steve-hilton"}, {"name": "Ethan Agarwal", "party": "Democratic", "path": "/ca/candidate/ethan-agarwal"}, {"name": "Toni Atkins", "party": "Democratic", "path": "/ca/candidate/toni-atkins"}, {"name": "Ian Calderon", "party": "Democratic", "path": "/ca/candidate/ian-calderon"}, {"name": "William Derek Grasty", "party": "Democratic", "path": "/ca/candidate/william-derek-grasty"}, {"name": "Eleni Kounalakis", "party": "Democratic", "path": "/ca/candidate/eleni-kounalakis"}, {"name": "Matt Mahan", "party": "Democratic", "path": "/ca/candidate/matt-mahan"}, {"name": "Thunder Parley", "party": "Democratic", "path": "/ca/candidate/thunder-parley"}, {"name": "Katie Porter", "party": "Democratic", "path": "/ca/candidate/katie-porter"}, {"name": "Raji Rab", "party": "Democratic", "path": "/ca/candidate/raji-rab"}, {"name": "George Slivka", "party": "Democratic", "path": "/ca/candidate/george-slivka"}, {"name": "Tom Steyer", "party": "Democratic", "path": "/ca/candidate/tom-steyer"}, {"name": "Eric Swalwell", "party": "Democratic", "path": "/ca/candidate/eric-swalwell"}, {"name": "Tony Thurmond", "party": "Democratic", "path": "/ca/candidate/tony-thurmond"}, {"name": "Antonio Villaraigosa", "party": "Democratic", "path": "/ca/candidate/antonio-villaraigosa"}, {"name": "Betty Yee", "party": "Democratic", "path": "/ca/candidate/betty-yee"}, {"name": "Chad Bianco", "party": "Republican", "path": "/ca/candidate/chad-bianco"}, {"name": "Brandon Jones", "party": "Republican", "path": "/ca/candidate/brandon-jones"}, {"name": "Jon Slavet", "party": "Republican", "path": "/ca/candidate/jon-slavet"}, {"name": "Leo Zacky", "party": "Republican", "path": "/ca/candidate/leo-zacky"}, {"name": "Elaine Culotti", "party": "No party preference", "path": "/ca/candidate/elaine-culotti"}, {"name": "LivingForGod AndCountry DeMott", "party": "No party preference", "path": "/ca/candidate/livingforgod-andcountry-demott"}, {"name": "Serge Fiankan", "party": "No party preference", "path": "/ca/candidate/serge-fiankan"}, {"name": "Jon Henderson", "party": "No party preference", "path": "/ca/candidate/jon-henderson"}, {"name": "Lewis Herms", "party": "No party preference", "path": "/ca/candidate/lewis-herms"}, {"name": "Dawit Kellel", "party": "No party preference", "path": "/ca/candidate/dawit-kellel"}, {"name": "Daniel Mercuri", "party": "No party preference", "path": "/ca/candidate/daniel-mercuri"}, {"name": "Reza Safarnejad", "party": "No party preference", "path": "/ca/candidate/reza-safarnejad"}, {"name": "Christine Sarmiento", "party": "No party preference", "path": "/ca/candidate/christine-sarmiento"}, {"name": "Nancy Young", "party": "No party preference", "path": "/ca/candidate/nancy-young"}, {"name": "Ramsey Robinson", "party": "Peace and Freedom", "path": "/ca/candidate/ramsey-robinson"}, {"name": "Che Ahn", "party": "Republican", "path": "/ca/candidate/che-ahn"}, {"name": "Butch Ware", "party": "Green", "path": "/ca/candidate/butch-ware"}], "cand:/ca/candidate/xavier-becerra": {"coh": 5129836.0, "contributions": 11283904.0, "expenditures": 18298411.0}, "cand:/ca/candidate/steve-hilton": {"coh": 1724547.0, "contributions": 12875324.0, "expenditures": 14825927.0}, "race:CO": [{"name": "Philip Weiser", "party": "Democratic", "path": "/co/candidate/philip-weiser"}, {"name": "Erik Underwood", "party": "Approval Voting", "path": "/co/candidate/erik-underwood"}, {"name": "Eric Mulder", "party": "Libertarian", "path": "/co/candidate/eric-mulder"}, {"name": "Kelsey Heikkinen", "party": "No Labels", "path": "/co/candidate/kelsey-heikkinen"}, {"name": "Abass Yaya Bamba", "party": "No Labels", "path": "/co/candidate/abass-yaya-bamba"}, {"name": "Shawn Bennett", "party": "Unaffiliated", "path": "/co/candidate/shawn-bennett"}, {"name": "Willow Jon Collamer", "party": "Unaffiliated", "path": "/co/candidate/willow-jon-collamer"}, {"name": "Marla Fernandez", "party": "Unaffiliated", "path": "/co/candidate/marla-fernandez"}, {"name": "Danny Fish", "party": "Unaffiliated", "path": "/co/candidate/danny-fish"}, {"name": "Christian Komor", "party": "Unaffiliated", "path": "/co/candidate/christian-komor"}, {"name": "Greg Lopez", "party": "Unaffiliated", "path": "/co/candidate/greg-lopez"}, {"name": "Gregory Roebuck", "party": "Unaffiliated", "path": "/co/candidate/gregory-roebuck"}, {"name": "Rachel Suh", "party": "Unaffiliated", "path": "/co/candidate/rachel-suh"}, {"name": "Michael Bennet", "party": "Democratic", "path": "/co/candidate/michael-bennet"}, {"name": "Carmen Broesder", "party": "Democratic", "path": "/co/candidate/carmen-broesder"}, {"name": "David Hughes", "party": "Democratic", "path": "/co/candidate/david-hughes"}, {"name": "Anthony Martinez", "party": "Democratic", "path": "/co/candidate/anthony-martinez"}, {"name": "William Moses", "party": "Democratic", "path": "/co/candidate/william-moses"}, {"name": "Mark Baisley", "party": "Republican", "path": "/co/candidate/mark-baisley"}, {"name": "Scott Bottoms", "party": "Republican", "path": "/co/candidate/scott-bottoms"}, {"name": "Bob C Brinkerhoff", "party": "Republican", "path": "/co/candidate/bob-c-brinkerhoff"}, {"name": "John L Brooks", "party": "Republican", "path": "/co/candidate/john-l-brooks"}, {"name": "Jason Ray Clark", "party": "Republican", "path": "/co/candidate/jason-ray-clark"}, {"name": "Stevan Gess", "party": "Republican", "path": "/co/candidate/stevan-gess"}, {"name": "Jon Gray-Ginsberg", "party": "Republican", "path": "/co/candidate/jon-gray-ginsberg"}, {"name": "Joshua Griffin", "party": "Republican", "path": "/co/candidate/joshua-griffin"}, {"name": "Robin Jones", "party": "Republican", "path": "/co/candidate/robin-jones"}, {"name": "Teri Ann Kear", "party": "Republican", "path": "/co/candidate/teri-ann-kear"}, {"name": "Barbara Kirkmeyer", "party": "Republican", "path": "/co/candidate/barbara-kirkmeyer"}, {"name": "Victor Marx", "party": "Republican", "path": "/co/candidate/victor-marx"}, {"name": "Will Mcbride", "party": "Republican", "path": "/co/candidate/will-mcbride"}, {"name": "Jason V Mikesell", "party": "Republican", "path": "/co/candidate/jason-v-mikesell"}, {"name": "Robert Moore", "party": "Republican", "path": "/co/candidate/robert-moore"}, {"name": "Alexander Mugatu", "party": "Republican", "path": "/co/candidate/alexander-mugatu"}, {"name": "Maria Orms", "party": "Republican", "path": "/co/candidate/maria-orms"}, {"name": "Katie Pierce", "party": "Republican", "path": "/co/candidate/katie-pierce"}, {"name": "Jim Lennart Rundberg", "party": "Republican", "path": "/co/candidate/jim-lennart-rundberg"}, {"name": "Kelvin Millard Wimberly", "party": "Republican", "path": "/co/candidate/kelvin-millard-wimberly"}, {"name": "Paul Noel Fiorino", "party": "Unity", "path": "/co/candidate/paul-noel-fiorino"}, {"name": "Jeff Peckman", "party": "Unity", "path": "/co/candidate/jeff-peckman"}], "cand:/co/candidate/philip-weiser": {"coh": 0.0, "contributions": 6951032.0, "expenditures": 6788538.0}, "cand:/co/candidate/victor-marx": {"coh": 0.0, "contributions": 2935521.0, "expenditures": 2767482.0}, "cand:/co/candidate/greg-lopez": {"coh": 0.0, "contributions": 84692.0, "expenditures": 85378.0}, "race:FL": [{"name": "Brandon McIntyre", "party": "Constitution", "path": "/fl/candidate/brandon-mcintyre"}, {"name": "Surindar Bedi", "party": "No Affiliation", "path": "/fl/candidate/surindar-bedi"}, {"name": "Jeff Datto", "party": "No Affiliation", "path": "/fl/candidate/jeff-datto"}, {"name": "Moliere Dimanche", "party": "No Affiliation", "path": "/fl/candidate/moliere-dimanche"}, {"name": "Insley Darris Corri Evans Sr", "party": "No Affiliation", "path": "/fl/candidate/insley-darris-corri-evans-sr"}, {"name": "Neil Gillespie", "party": "No Affiliation", "path": "/fl/candidate/neil-gillespie"}, {"name": "Mourice Hylton", "party": "No Affiliation", "path": "/fl/candidate/mourice-hylton"}, {"name": "Holly Klask", "party": "No Affiliation", "path": "/fl/candidate/holly-klask"}, {"name": "Andrea Lynn Klink", "party": "No Affiliation", "path": "/fl/candidate/andrea-lynn-klink"}, {"name": "Jason Pizzo", "party": "No Affiliation", "path": "/fl/candidate/jason-pizzo-can"}, {"name": "Frank J. Russo", "party": "No Affiliation", "path": "/fl/candidate/frank-j-russo"}, {"name": "David Wayne Gizmo Wexler", "party": "No Affiliation", "path": "/fl/candidate/david-wayne-gizmo-wexler"}, {"name": "Richard P Dembinsky", "party": "No Affiliation", "path": "/fl/candidate/richard-paul-dembinsky-can"}, {"name": "Rodney Glover", "party": "No Affiliation", "path": "/fl/candidate/rodney-glover"}, {"name": "Erik Edward Morris", "party": "No Affiliation", "path": "/fl/candidate/erik-edward-morris"}, {"name": "Faith E. Antonio", "party": "Democratic", "path": "/fl/candidate/faith-e-antonio"}, {"name": "Evelyn Castillo-Bach", "party": "Democratic", "path": "/fl/candidate/evelyn-castillo-bach"}, {"name": "Jerry Demings", "party": "Democratic", "path": "/fl/candidate/jerry-demings"}, {"name": "Thomas E. Fernandez", "party": "Democratic", "path": "/fl/candidate/thomas-e-fernandez"}, {"name": "Dayna Marie Foster", "party": "Democratic", "path": "/fl/candidate/dayna-marie-foster"}, {"name": "Indony Pierre Jean Baptiste", "party": "Democratic", "path": "/fl/candidate/indony-pierre-jean-baptiste"}, {"name": "David Jolly", "party": "Democratic", "path": "/fl/candidate/david-jolly"}, {"name": "Dotie Joseph", "party": "Democratic", "path": "/fl/candidate/dotie-joseph-can"}, {"name": "Charles A Lewis I", "party": "Democratic", "path": "/fl/candidate/charles-a-lewis-i"}, {"name": "Kenneth Norman", "party": "Democratic", "path": "/fl/candidate/kenneth-norman"}, {"name": "Donald J Peterson", "party": "Democratic", "path": "/fl/candidate/donald-j-peterson"}, {"name": "Christopher Powell", "party": "Democratic", "path": "/fl/candidate/christopher-powell"}, {"name": "Jessica Vernekar", "party": "Democratic", "path": "/fl/candidate/jessica-vernekar"}, {"name": "Scott Jewett", "party": "Libertarian", "path": "/fl/candidate/scott-jewett"}, {"name": "William Todd Andros", "party": "Republican", "path": "/fl/candidate/william-todd-andros"}, {"name": "Jay Collins", "party": "Republican", "path": "/fl/candidate/jay-collins"}, {"name": "Shea Cruel", "party": "Republican", "path": "/fl/candidate/shea-cruel"}, {"name": "Byron Donalds", "party": "Republican", "path": "/fl/candidate/byron-donalds-can"}, {"name": "James Fishback", "party": "Republican", "path": "/fl/candidate/james-fishback"}, {"name": "Jim Holcomb", "party": "Republican", "path": "/fl/candidate/jim-holcomb"}, {"name": "Daniel J Imperato", "party": "Republican", "path": "/fl/candidate/daniel-j-imperato"}, {"name": "John Joseph Mercadante", "party": "Republican", "path": "/fl/candidate/john-joseph-mercadante-can"}, {"name": "Bill Reicherter", "party": "Republican", "path": "/fl/candidate/bill-reicherter"}, {"name": "Paul Renner", "party": "Republican", "path": "/fl/candidate/paul-renner-can"}, {"name": "Rachel Rodriguez", "party": "Republican", "path": "/fl/candidate/rachel-rodriguez"}, {"name": "James Shaw", "party": "Republican", "path": "/fl/candidate/james-shaw"}, {"name": "Caneste Succe", "party": "Republican", "path": "/fl/candidate/caneste-succe"}, {"name": "Matthew Edward Taylor", "party": "Republican", "path": "/fl/candidate/matthew-edward-taylor"}, {"name": "Bobby Williams Jr", "party": "Republican", "path": "/fl/candidate/bobby-williams-jr"}], "cand:/fl/candidate/david-jolly": {"coh": 0.0, "contributions": 2814312.0, "expenditures": 1796181.0}, "cand:/fl/candidate/byron-donalds-can": {"coh": 0.0, "contributions": 65627327.0, "expenditures": 9558632.0}, "race:GA": [{"name": "Keisha L Bottoms", "party": "Democratic", "path": "/ga/candidate/keisha-l-bottoms"}, {"name": "Rick Jackson", "party": "Republican", "path": "/ga/candidate/rick-jackson"}, {"name": "Burt Jones", "party": "Republican", "path": "/ga/candidate/burt-jones"}, {"name": "Olu Brown", "party": "Democratic", "path": "/ga/candidate/olu-brown"}, {"name": "Geoff Duncan", "party": "Democratic", "path": "/ga/candidate/geoff-duncan"}, {"name": "Jason Esteves", "party": "Democratic", "path": "/ga/candidate/jason-esteves"}, {"name": "Derrick Jackson", "party": "Democratic", "path": "/ga/candidate/derrick-jackson"}, {"name": "Ruwa Romman", "party": "Democratic", "path": "/ga/candidate/ruwa-romman"}, {"name": "Mike Thurmond", "party": "Democratic", "path": "/ga/candidate/mike-thurmond"}, {"name": "Chris Carr", "party": "Republican", "path": "/ga/candidate/chris-carr"}, {"name": "Clark Dean", "party": "Republican", "path": "/ga/candidate/clark-dean"}, {"name": "Gregg Kirkpatrick", "party": "Republican", "path": "/ga/candidate/gregg-kirkpatrick"}, {"name": "Brad Raffensperger", "party": "Republican", "path": "/ga/candidate/brad-raffensperger"}, {"name": "Tom Williams", "party": "Republican", "path": "/ga/candidate/tom-williams"}, {"name": "Ken Yasger", "party": "Republican", "path": "/ga/candidate/ken-yasger"}], "cand:/ga/candidate/keisha-l-bottoms": {"coh": 0.0, "contributions": 2665880.0, "expenditures": 2603060.0}, "cand:/ga/candidate/rick-jackson": {"coh": 0.0, "contributions": 73526815.0, "expenditures": 65672560.0}, "race:IA": [{"name": "Rob Sand", "party": "Democratic", "path": "/ia/candidate/rob-sand"}, {"name": "Zach Lahn", "party": "Republican", "path": "/ia/candidate/zach-lahn"}, {"name": "Nicholas Gluba", "party": "Libertarian", "path": "/ia/candidate/nicholas-gluba"}, {"name": "Julie Stauch", "party": "Democratic", "path": "/ia/candidate/julie-stauch"}, {"name": "Eddie Andrews", "party": "Republican", "path": "/ia/candidate/eddie-andrews"}, {"name": "Randy Feenstra", "party": "Republican", "path": "/ia/candidate/randy-feenstra"}, {"name": "Bradley Sherman", "party": "Republican", "path": "/ia/candidate/bradley-sherman"}, {"name": "Adam Steen", "party": "Republican", "path": "/ia/candidate/adam-steen"}], "cand:/ia/candidate/rob-sand": {"coh": 0.0, "contributions": 9572747.0, "expenditures": 3852619.0}, "cand:/ia/candidate/zach-lahn": {"coh": 0.0, "contributions": 163603.0, "expenditures": 7694.0}, "race:ID": [{"name": "Brad Little", "party": "Republican", "path": "/id/candidate/brad-little"}, {"name": "Terri Pickens", "party": "Democratic", "path": "/id/candidate/terri-pickens"}, {"name": "Paul Sand", "party": "Libertarian", "path": "/id/candidate/paul-sand"}, {"name": "John Stegner", "party": "Unaffiliated", "path": "/id/candidate/john-stegner"}, {"name": "Jacob Burnett", "party": "Independent", "path": "/id/candidate/jacob-burnett"}, {"name": "Maxine Durand", "party": "Democratic", "path": "/id/candidate/maxine-durand"}, {"name": "Jill Kirkham", "party": "Democratic", "path": "/id/candidate/jill-kirkham"}, {"name": "Chanelle Torrez", "party": "Democratic", "path": "/id/candidate/chanelle-torrez"}, {"name": "Melissa Robinson", "party": "Libertarian", "path": "/id/candidate/melissa-robinson"}, {"name": "Sean Crystal", "party": "Republican", "path": "/id/candidate/sean-crystal"}, {"name": "Mark Fitzpatrick", "party": "Republican", "path": "/id/candidate/mark-fitzpatrick"}, {"name": "Ethan Giles", "party": "Republican", "path": "/id/candidate/ethan-giles"}, {"name": "Ron James", "party": "Republican", "path": "/id/candidate/ron-james"}, {"name": "Justin Plante", "party": "Republican", "path": "/id/candidate/justin-plante"}], "cand:/id/candidate/terri-pickens": {"coh": 0.0, "contributions": 136953.0, "expenditures": 93119.0}, "cand:/id/candidate/brad-little": {"coh": 0.0, "contributions": 2057743.0, "expenditures": 1307328.0}, "race:IL": [{"name": "JB Pritzker", "party": "Democratic", "path": "/il/candidate/jb-pritzker"}, {"name": "Darren Bailey", "party": "Republican", "path": "/il/candidate/darren-bailey"}, {"name": "Gary Pierce", "party": "Independence", "path": "/il/candidate/gary-pierce"}, {"name": "Patricia Tillman", "party": "Democratic", "path": "/il/candidate/patricia-tillman"}, {"name": "Ted Dabrowski", "party": "Republican", "path": "/il/candidate/ted-dabrowski"}, {"name": "Rick Heidner", "party": "Republican", "path": "/il/candidate/rick-heidner"}, {"name": "James Mendrick", "party": "Republican", "path": "/il/candidate/james-mendrick"}, {"name": "Joseph Severino", "party": "Republican", "path": "/il/candidate/joseph-severino"}, {"name": "Max Solomon", "party": "Republican", "path": "/il/candidate/max-solomon"}], "cand:/il/candidate/jb-pritzker": {"coh": 3141018.0, "contributions": 25619035.0, "expenditures": 26626897.0}, "cand:/il/candidate/darren-bailey": {"coh": 127990.0, "contributions": 2166962.0, "expenditures": 1981292.0}, "race:MI": [{"name": "Michael Edward Duggan Jr", "party": "Independent", "path": "/mi/candidate/michael-edward-duggan-jr"}, {"name": "Jocelyn Benson", "party": "Democratic", "path": "/mi/candidate/jocelyn-benson-can"}, {"name": "Garlin Gilchrist II", "party": "Democratic", "path": "/mi/candidate/garlin-gilchrist"}, {"name": "Kevin Hogan", "party": "Democratic", "path": "/mi/candidate/kevin-hogan"}, {"name": "Marni Sawicki", "party": "Democratic", "path": "/mi/candidate/marni-sawicki"}, {"name": "Chris Swanson", "party": "Democratic", "path": "/mi/candidate/chris-swanson"}, {"name": "Mike Cox", "party": "Republican", "path": "/mi/candidate/mike-cox"}, {"name": "Joyce Gipson", "party": "Republican", "path": "/mi/candidate/joyce-gipson"}, {"name": "Anthony Hudson", "party": "Republican", "path": "/mi/candidate/anthony-hudson"}, {"name": "John James", "party": "Republican", "path": "/mi/candidate/john-james"}, {"name": "Perry Johnson", "party": "Republican", "path": "/mi/candidate/perry-johnson"}, {"name": "Tom Leonard", "party": "Republican", "path": "/mi/candidate/tom-leonard-can"}, {"name": "Aric Nesbitt", "party": "Republican", "path": "/mi/candidate/aric-nesbitt-can"}, {"name": "Ralph Rebandt", "party": "Republican", "path": "/mi/candidate/ralph-rebandt"}, {"name": "Evan Space", "party": "Republican", "path": "/mi/candidate/evan-space"}, {"name": "Karla Wagner", "party": "Republican", "path": "/mi/candidate/karla-wagner"}], "cand:/mi/candidate/jocelyn-benson-can": {"coh": 0.0, "contributions": 5958887.0, "expenditures": 3533586.0}, "cand:/mi/candidate/john-james": {"coh": 0.0, "contributions": 4492470.0, "expenditures": 2144549.0}, "race:MN": [{"name": "Michael Newcome", "party": "Unaffiliated", "path": "/mn/candidate/michael-newcome"}, {"name": "Brad Kohler", "party": "Independent", "path": "/mn/candidate/brad-kohler"}, {"name": "Tim Walz", "party": "Democratic", "path": "/mn/candidate/tim-walz-pcc"}, {"name": "Rick DeVoe", "party": "Democratic", "path": "/mn/candidate/rick-devoe"}, {"name": "Thomas Evenstad", "party": "Democratic", "path": "/mn/candidate/thomas-evenstad"}, {"name": "Paul Ference", "party": "Democratic", "path": "/mn/candidate/paul-ference"}, {"name": "Bill E Gates Jr", "party": "Democratic", "path": "/mn/candidate/bill-e-gates-jr"}, {"name": "Tim Holden", "party": "Democratic", "path": "/mn/candidate/tim-holden-pcc"}, {"name": "Amy Klobuchar", "party": "Democratic", "path": "/mn/candidate/amy-klobuchar"}, {"name": "Kobey Layne", "party": "Democratic", "path": "/mn/candidate/kobey-layne"}, {"name": "Ole Savior", "party": "Democratic", "path": "/mn/candidate/ole-savior"}, {"name": "Christopher Lovell Seymore", "party": "Democratic", "path": "/mn/candidate/christopher-lovell-seymore-pcc"}, {"name": "Po Vang", "party": "Democratic", "path": "/mn/candidate/po-vang"}, {"name": "Mohammad Wazwaz", "party": "Democratic", "path": "/mn/candidate/mohammad-wazwaz"}, {"name": "Peggy Bennett", "party": "Republican", "path": "/mn/candidate/peggy-bennett-pcc"}, {"name": "Lisa Demuth", "party": "Republican", "path": "/mn/candidate/lisa-demuth-pcc"}, {"name": "Raul J Estrada Sr", "party": "Republican", "path": "/mn/candidate/raul-j-estrada-sr"}, {"name": "Scott Jensen", "party": "Republican", "path": "/mn/candidate/scott-mitchell-jensen-pcc"}, {"name": "Jeff Johnson", "party": "Republican", "path": "/mn/candidate/jeff-johnson"}, {"name": "Patrick Knight", "party": "Republican", "path": "/mn/candidate/patrick-knight"}, {"name": "John Thomas Krhin", "party": "Republican", "path": "/mn/candidate/john-thomas-krhin"}, {"name": "Mike Lindell", "party": "Republican", "path": "/mn/candidate/mike-lindell"}, {"name": "Chris Madel", "party": "Republican", "path": "/mn/candidate/chris-madel"}, {"name": "Ross Nova", "party": "Republican", "path": "/mn/candidate/ross-nova"}, {"name": "Phillip Parrish", "party": "Republican", "path": "/mn/candidate/phillip-parrish-1"}, {"name": "Kendall Qualls", "party": "Republican", "path": "/mn/candidate/kendall-qualls-pcc"}, {"name": "Kristin Robbins", "party": "Republican", "path": "/mn/candidate/kristin-robbins-pcc"}], "cand:/mn/candidate/amy-klobuchar": {"coh": 3859683.0, "contributions": 7053950.0, "expenditures": 3195567.0}, "cand:/mn/candidate/mike-lindell": {"coh": 11704.0, "contributions": 1001473.0, "expenditures": 1001250.0}, "race:NH": [{"name": "Jonathan Kiper", "party": "Independent", "path": "/nh/candidate/jonathan-kiper"}, {"name": "Cinde Warmington", "party": "Democratic", "path": "/nh/candidate/cinde-warmington"}, {"name": "Kelly Ayotte", "party": "Republican", "path": "/nh/candidate/kelly-ayotte"}, {"name": "Shaun Fife", "party": "Republican", "path": "/nh/candidate/shaun-fife"}], "cand:/nh/candidate/cinde-warmington": {"coh": 0.0, "contributions": 606192.0, "expenditures": 209544.0}, "cand:/nh/candidate/kelly-ayotte": {"coh": 0.0, "contributions": 3694856.0, "expenditures": 1406262.0}, "race:NM": [{"name": "Deb Haaland", "party": "Democratic", "path": "/nm/candidate/deb-haaland"}, {"name": "Greggory D Hull", "party": "Republican", "path": "/nm/candidate/greggory-d-hull"}, {"name": "Tristan Kumar", "party": "Independent", "path": "/nm/candidate/tristan-kumar"}, {"name": "Kenneth D Miyagishima", "party": "Independent", "path": "/nm/candidate/kenneth-d-miyagishima"}, {"name": "Gene Pettit", "party": "Independent", "path": "/nm/candidate/gene-pettit"}, {"name": "Sam Bregman", "party": "Democratic", "path": "/nm/candidate/sam-bregman"}, {"name": "James F Ellison", "party": "Republican", "path": "/nm/candidate/james-f-ellison"}, {"name": "Steve Lanier", "party": "Republican", "path": "/nm/candidate/steve-lanier"}, {"name": "Duke Rodriguez", "party": "Republican", "path": "/nm/candidate/duke-rodriguez"}, {"name": "Doug Turner", "party": "Republican", "path": "/nm/candidate/doug-turner"}], "cand:/nm/candidate/deb-haaland": {"coh": 0.0, "contributions": 13910580.0, "expenditures": 11511643.0}, "cand:/nm/candidate/greggory-d-hull": {"coh": 0.0, "contributions": 987856.0, "expenditures": 647302.0}, "race:NV": [{"name": "Joseph Lombardo", "party": "Republican", "path": "/nv/candidate/joseph-lombardo"}, {"name": "Aaron Ford", "party": "Democratic", "path": "/nv/candidate/aaron-ford"}, {"name": "Christopher Battenberg", "party": "No Political", "path": "/nv/candidate/christopher-battenberg"}, {"name": "Max Beck", "party": "No Political", "path": "/nv/candidate/max-beck"}, {"name": "Danielle Ford", "party": "No Political", "path": "/nv/candidate/danielle-ford"}, {"name": "Jordan Koteras", "party": "No Political", "path": "/nv/candidate/jordan-koteras"}, {"name": "Allen Rheinhart", "party": "No Political", "path": "/nv/candidate/allen-rheinhart"}, {"name": "Emilio Rodriguez", "party": "No Political", "path": "/nv/candidate/emilio-rodriguez"}, {"name": "John Scott", "party": "No Political", "path": "/nv/candidate/john-scott"}, {"name": "Sunshine Arterburn", "party": "Democratic", "path": "/nv/candidate/sunshine-arterburn"}, {"name": "Miqehl Bayfield", "party": "Democratic", "path": "/nv/candidate/miqehl-bayfield"}, {"name": "Emile Bouari", "party": "Democratic", "path": "/nv/candidate/emile-bouari"}, {"name": "James Cooper", "party": "Democratic", "path": "/nv/candidate/james-cooper"}, {"name": "Alexis Hill", "party": "Democratic", "path": "/nv/candidate/alexis-hill"}, {"name": "Donald Beaudry Jr.", "party": "Republican", "path": "/nv/candidate/donald-beaudry-jr"}, {"name": "Irina Hansen", "party": "Republican", "path": "/nv/candidate/irina-hansen"}, {"name": "M. Kameron Hawkins", "party": "Republican", "path": "/nv/candidate/m-kameron-hawkins"}, {"name": "Matthew Winterhawk", "party": "Republican", "path": "/nv/candidate/matthew-winterhawk"}, {"name": "Jose Zelaya", "party": "Republican", "path": "/nv/candidate/jose-zelaya"}, {"name": "Barak Zilberberg", "party": "Republican", "path": "/nv/candidate/barak-zilberberg"}], "cand:/nv/candidate/aaron-ford": {"coh": 0.0, "contributions": 4285307.0, "expenditures": 2786816.0}, "cand:/nv/candidate/joseph-lombardo": {"coh": 0.0, "contributions": 2275075.0, "expenditures": 3388835.0}, "race:NY": [{"name": "Kathy C Hochul", "party": "Democratic", "path": "/ny/candidate/kathy-c-hochul"}, {"name": "Bruce Blakeman", "party": "Republican", "path": "/ny/candidate/bruce-blakeman"}, {"name": "Larry Sharpe", "party": "Coalition", "path": "/ny/candidate/larry-sharpe"}, {"name": "Antonio Delgado", "party": "Democratic", "path": "/ny/candidate/antonio-delgado"}, {"name": "Elise M Stefanik", "party": "Republican", "path": "/ny/candidate/elise-m-stefanik"}], "cand:/ny/candidate/kathy-c-hochul": {"coh": 0.0, "contributions": 16594119.0, "expenditures": 12983887.0}, "cand:/ny/candidate/bruce-blakeman": {"coh": 0.0, "contributions": 13445025.0, "expenditures": 10455186.0}, "race:OH": [{"name": "Amy Acton", "party": "Democratic", "path": "/oh/candidate/amy-acton"}, {"name": "Vivek Ramaswamy", "party": "Republican", "path": "/oh/candidate/vivek-ramaswamy"}, {"name": "Don Kissick", "party": "Libertarian", "path": "/oh/candidate/don-kissick"}, {"name": "Tim Grady", "party": "No Affiliation", "path": "/oh/candidate/tim-grady"}, {"name": "Travis Vought", "party": "Libertarian", "path": "/oh/candidate/travis-vought"}, {"name": "Heather Hill", "party": "Republican", "path": "/oh/candidate/heather-hill"}, {"name": "Casey Putsch", "party": "Republican", "path": "/oh/candidate/casey-putsch"}, {"name": "Robert Sprague", "party": "Republican", "path": "/oh/candidate/robert-sprague-13504"}, {"name": "Renea Turner", "party": "Republican", "path": "/oh/candidate/renea-turner"}, {"name": "David Yost", "party": "Republican", "path": "/oh/candidate/david-yost-12822"}], "cand:/oh/candidate/amy-acton": {"coh": 0.0, "contributions": 10552470.0, "expenditures": 5531668.0}, "cand:/oh/candidate/vivek-ramaswamy": {"coh": 0.0, "contributions": 25555956.0, "expenditures": 19695657.0}, "race:PA": [{"name": "Josh Shapiro", "party": "Democratic", "path": "/pa/candidate/josh-shapiro"}, {"name": "Stacey L Garrity", "party": "Republican", "path": "/pa/candidate/stacey-l-garrity"}, {"name": "Bill Messner", "party": "Constitution", "path": "/pa/candidate/bill-messner"}], "cand:/pa/candidate/josh-shapiro": {"coh": 0.0, "contributions": 34960533.0, "expenditures": 10484498.0}, "cand:/pa/candidate/stacey-l-garrity": {"coh": 0.0, "contributions": 2545436.0, "expenditures": 1384989.0}, "race:SC": [{"name": "Jermaine L Johnson", "party": "Democratic", "path": "/sc/candidate/jermaine-l-johnson"}, {"name": "Alan Wilson", "party": "Republican", "path": "/sc/candidate/alan-wilson"}, {"name": "Pamela Evette", "party": "Republican", "path": "/sc/candidate/pamela-evette"}, {"name": "Mullins McLeod", "party": "Democratic", "path": "/sc/candidate/mullins-mcleod"}, {"name": "Billy Webster", "party": "Democratic", "path": "/sc/candidate/billy-webster"}, {"name": "Jacqueline H Dubose", "party": "Republican", "path": "/sc/candidate/jacqueline-h-dubose"}, {"name": "Joshua B Kimbrell", "party": "Republican", "path": "/sc/candidate/joshua-b-kimbrell"}, {"name": "Nancy Mace", "party": "Republican", "path": "/sc/candidate/nancy-mace"}, {"name": "Ralph W Norman", "party": "Republican", "path": "/sc/candidate/ralph-w-norman"}, {"name": "Thomas T Ravenell", "party": "Republican", "path": "/sc/candidate/thomas-t-ravenell"}, {"name": "Rom Reddy", "party": "Republican", "path": "/sc/candidate/rom-reddy"}], "cand:/sc/candidate/jermaine-l-johnson": {"coh": 0.0, "contributions": 753609.0, "expenditures": 618731.0}, "cand:/sc/candidate/alan-wilson": {"coh": 0.0, "contributions": 62585.0, "expenditures": 492252.0}, "race:TX": [{"name": "Greg Abbott", "party": "Republican", "path": "/tx/candidate/greg-abbott"}, {"name": "Gina Hinojosa", "party": "Democratic", "path": "/tx/candidate/gina-hinojosa-coh"}, {"name": "Pat Dixon", "party": "Libertarian", "path": "/tx/candidate/pat-dixon"}, {"name": "Sarah Bowman Cunningham", "party": "Independent", "path": "/tx/candidate/sarah-bowman-cunningham"}, {"name": "Blas Eugenio Padrino", "party": "Independent", "path": "/tx/candidate/blas-eugenio-padrino"}, {"name": "Jenn Mack Raphoon", "party": "Independent", "path": "/tx/candidate/jenn-mack-raphoon"}, {"name": "Janis Richards", "party": "Independent", "path": "/tx/candidate/janis-richards"}, {"name": "Demetra Jefferson-Wysinger", "party": "Independent", "path": "/tx/candidate/demetra-jefferson-wysinger"}, {"name": "Patricia Abrego", "party": "Democratic", "path": "/tx/candidate/patricia-abrego"}, {"name": "Chris Bell", "party": "Democratic", "path": "/tx/candidate/chris-bell"}, {"name": "Bobby Cole", "party": "Democratic", "path": "/tx/candidate/bobby-cole"}, {"name": "Carlton Hart", "party": "Democratic", "path": "/tx/candidate/carlton-hart"}, {"name": "Jose Navarro Balbuena", "party": "Democratic", "path": "/tx/candidate/jose-navarro-balbuena"}, {"name": "Nick J Pappas", "party": "Democratic", "path": "/tx/candidate/nick-j-pappas"}, {"name": "Faizan Syed", "party": "Democratic", "path": "/tx/candidate/faizan-syed"}, {"name": "Meagan Tehseldar", "party": "Democratic", "path": "/tx/candidate/meagan-tehseldar"}, {"name": "Zachary Vance", "party": "Democratic", "path": "/tx/candidate/zachary-vance"}, {"name": "Angela Villescaz", "party": "Democratic", "path": "/tx/candidate/angela-villescaz"}, {"name": "Andrew White", "party": "Democratic", "path": "/tx/candidate/andrew-white"}, {"name": "Bob Achgill", "party": "Republican", "path": "/tx/candidate/bob-achgill"}, {"name": "Evelyn Brooks", "party": "Republican", "path": "/tx/candidate/evelyn-brooks"}, {"name": "Peter Chambers", "party": "Republican", "path": "/tx/candidate/peter-chambers"}, {"name": "Charles Crouch", "party": "Republican", "path": "/tx/candidate/charles-crouch"}, {"name": "Arturo Espinosa", "party": "Republican", "path": "/tx/candidate/arturo-espinosa"}, {"name": "Mark Goloby", "party": "Republican", "path": "/tx/candidate/mark-goloby"}, {"name": "Kenneth Hyde", "party": "Republican", "path": "/tx/candidate/kenneth-hyde"}, {"name": "Stephen Samuelson", "party": "Republican", "path": "/tx/candidate/stephen-samuelson"}, {"name": "Ronnie Tullos", "party": "Republican", "path": "/tx/candidate/ronnie-tullos"}, {"name": "Nathaniel Welch", "party": "Republican", "path": "/tx/candidate/nathaniel-welch"}], "cand:/tx/candidate/gina-hinojosa-coh": {"coh": 3002416.0, "contributions": 8589462.0, "expenditures": 5650650.0}, "cand:/tx/candidate/greg-abbott": {"coh": 67461299.0, "contributions": 71434049.0, "expenditures": 169132802.0}, "race:WI": [{"name": "Jill Ferguson", "party": "Green", "path": "/wi/candidate/jill-ferguson"}, {"name": "Crystal Harper", "party": "Independent", "path": "/wi/candidate/crystal-harper"}, {"name": "David King", "party": "Independent", "path": "/wi/candidate/david-king"}, {"name": "Travis Swenby", "party": "Independent", "path": "/wi/candidate/travis-swenby"}, {"name": "Kirk Bangstad", "party": "Democratic", "path": "/wi/candidate/kirk-bangstad"}, {"name": "Mandela Barnes", "party": "Democratic", "path": "/wi/candidate/mandela-barnes"}, {"name": "David Crowley", "party": "Democratic", "path": "/wi/candidate/david-crowley"}, {"name": "Francesca Hong", "party": "Democratic", "path": "/wi/candidate/francesca-hong"}, {"name": "Brett Hulsey", "party": "Democratic", "path": "/wi/candidate/brett-hulsey"}, {"name": "Sara Rodriguez", "party": "Democratic", "path": "/wi/candidate/sara-rodriguez"}, {"name": "Zachary Roper", "party": "Democratic", "path": "/wi/candidate/zachary-roper"}, {"name": "Kelda Roys", "party": "Democratic", "path": "/wi/candidate/kelda-roys"}, {"name": "Ryan Strnad", "party": "Democratic", "path": "/wi/candidate/ryan-strnad"}, {"name": "Josh Schoemann", "party": "Republican", "path": "/wi/candidate/josh-schoemann"}, {"name": "Tom Tiffany", "party": "Republican", "path": "/wi/candidate/tom-tiffany"}], "cand:/wi/candidate/francesca-hong": {"coh": 0.0, "contributions": 13951.0, "expenditures": 11196.0}, "cand:/wi/candidate/tom-tiffany": {"coh": 0.0, "contributions": 1.0, "expenditures": 0.0}, "race:WY": [{"name": "Ken Casner", "party": "Democratic", "path": "/wy/candidate/ken-casner"}, {"name": "Eric Barlow", "party": "Republican", "path": "/wy/candidate/eric-barlow"}, {"name": "Brent Bien", "party": "Republican", "path": "/wy/candidate/brent-bien"}, {"name": "Megan Degenfelder", "party": "Republican", "path": "/wy/candidate/megan-degenfelder"}], "cand:/wy/candidate/ken-casner": {"coh": 0.0, "contributions": 0.0, "expenditures": 0.0}, "cand:/wy/candidate/megan-degenfelder": {"coh": 0.0, "contributions": 5226.0, "expenditures": 460553.0}}